datasette_extract/__init__.py
datasette_extract/static/extract.css
datasette_extract/static/heic2any-0.0.4.min.js
datasette_extract/templates/_extract_base_styles.html
datasette_extract/templates/_extract_drop_handler.html
datasette_extract/templates/extract.html
datasette_extract/templates/extract_create_table.html
datasette_extract/templates/extract_progress.html
datasette_extract/templates/extract_to_table.html
datasette_extract-0.1a10.dist-info/licenses/LICENSE
tests/conftest.py
tests/test_web.py
datasette_extract-0.1a10.dist-info/METADATA
datasette_extract-0.1a10.dist-info/WHEEL
datasette_extract-0.1a10.dist-info/entry_points.txt
datasette_extract-0.1a10.dist-info/top_level.txt
datasette_extract-0.1a10.dist-info/RECORD
