Metadata-Version: 2.4
Name: datasette-extract
Version: 0.1a10
Summary: Import unstructured data (text and images) into structured tables
Author: Simon Willison
License: Apache-2.0
Project-URL: Homepage, https://github.com/datasette/datasette-extract
Project-URL: Changelog, https://github.com/datasette/datasette-extract/releases
Project-URL: Issues, https://github.com/datasette/datasette-extract/issues
Project-URL: CI, https://github.com/datasette/datasette-extract/actions
Classifier: Framework :: Datasette
Classifier: License :: OSI Approved :: Apache Software License
Requires-Python: >=3.9
License-File: LICENSE
Requires-Dist: datasette>=1.0a12
Requires-Dist: datasette-secrets>=0.1a2
Requires-Dist: llm>=0.24
Requires-Dist: llm-openai-plugin
Requires-Dist: sqlite-utils
Requires-Dist: openai>=1.0
Requires-Dist: ijson
Requires-Dist: python-ulid
Requires-Dist: starlette
Provides-Extra: test
Requires-Dist: pytest; extra == "test"
Requires-Dist: pytest-asyncio; extra == "test"
Requires-Dist: pytest-recording; extra == "test"
Dynamic: license-file
